{
  "name": "Боевое слаживание",
  "description": "Вас учили встречаться в бою с бесчисленными ужасами вселенной в составе подготовленного отряда. Вы получаете преимущество к проверкам, предпринятым, чтобы сопротивляться состоянию Страх, а также +1 успех к проверкам Дисциплины за каждого соратника, обладающего талантом Боевое слаживание и находящегося в этой же зоне. Если в вашей группе есть второй обладатель таланта Боевое слаживание, вы оба можете приобрести его ещё раз, чтобы получить следующее преимущество: \n<b>Истребительная команда</b>: всякий раз, когда вы находитесь в одной зоне с другим членом вашей команды, что имеет талант Боевое слаживание, вы можете (но не обязаны) действовать сразу после него. При этом вы получите +1 успех ко всем проверкам.",
  "requirements": [
  {
	  "type": "skill_improvement",
	  "skill": "Дисциплина",
	  "amount": 1
  }
  ],
  "isMultiple": true,
  "maxMultiple": 2
}